hanbitco/__init__.py
hanbitco/api.py
hanbitco/constants.py
hanbitco/error.py
hanbitco/utils.py
hanbitco_api-1.1.0.dist-info/LICENSE
hanbitco_api-1.1.0.dist-info/METADATA
hanbitco_api-1.1.0.dist-info/WHEEL
hanbitco_api-1.1.0.dist-info/top_level.txt
hanbitco_api-1.1.0.dist-info/RECORD
