Metadata-Version: 2.1
Name: hanbitco-api
Version: 1.1.0
Summary: Offical API Python Wrapper for Hanbitco Exchange
Home-page: https://github.com/plutusds/hanbitco-api
Author: Kevin Kim
Author-email: kevink1103@plutusds.com
License: MIT
Download-URL: https://github.com/plutusds/hanbitco-api/dist/hanbitco_api-1.1.0-py3-none-any.whl
Keywords: cryptocurrency,exchange,api
Platform: UNKNOWN
Classifier: Programming Language :: Python :: 3.6
Classifier: Programming Language :: Python :: 3.7
Classifier: Programming Language :: Python :: 3.8
Classifier: Programming Language :: Python :: 3.9
Requires-Python: >=3.6
